[{"name":"sql.active_record","payload":{"sql":"SELECT  \"offers\".* FROM \"offers\"  WHERE (completed = 'n') LIMIT 5 OFFSET 0","name":"Offer Load","connection_id":70131598302600,"binds":[]},"time":"2014-03-21T20:54:50+00:00","transaction_id":"a5fe53095b653099bcf1","end":"2014-03-21T20:54:50+00:00","duration":0.118},{"name":"sql.active_record","payload":{"sql":"SELECT  \"users\".* FROM \"users\" INNER JOIN \"offers_users\" ON \"users\".\"id\" = \"offers_users\".\"user_id\" WHERE \"offers_users\".\"offer_id\" = 150 LIMIT 1","name":"User Load","connection_id":70131598302600,"binds":[]},"time":"2014-03-21T20:54:50+00:00","transaction_id":"a5fe53095b653099bcf1","end":"2014-03-21T20:54:50+00:00","duration":0.11299999999999999},{"name":"sql.active_record","payload":{"sql":"SELECT  \"users\".* FROM \"users\"  WHERE \"users\".\"id\" = 1 LIMIT 1","name":"User Load","connection_id":70131598302600,"binds":[]},"time":"2014-03-21T20:54:50+00:00","transaction_id":"a5fe53095b653099bcf1","end":"2014-03-21T20:54:50+00:00","duration":0.108},{"name":"sql.active_record","payload":{"sql":"SELECT \"users\".* FROM \"users\" INNER JOIN \"offers_users\" ON \"users\".\"id\" = \"offers_users\".\"user_id\" WHERE \"offers_users\".\"offer_id\" = 150","name":"User Load","connection_id":70131598302600,"binds":[]},"time":"2014-03-21T20:54:50+00:00","transaction_id":"a5fe53095b653099bcf1","end":"2014-03-21T20:54:50+00:00","duration":0.19799999999999998},{"name":"sql.active_record","payload":{"sql":"SELECT \"products\".* FROM \"products\" INNER JOIN \"offers_products\" ON \"products\".\"id\" = \"offers_products\".\"product_id\" WHERE \"offers_products\".\"offer_id\" = 150","name":"Product Load","connection_id":70131598302600,"binds":[]},"time":"2014-03-21T20:54:50+00:00","transaction_id":"a5fe53095b653099bcf1","end":"2014-03-21T20:54:50+00:00","duration":0.111},{"name":"sql.active_record","payload":{"sql":"SELECT  \"users\".* FROM \"users\"  WHERE \"users\".\"id\" = 2 LIMIT 1","name":"User Load","connection_id":70131598302600,"binds":[]},"time":"2014-03-21T20:54:50+00:00","transaction_id":"a5fe53095b653099bcf1","end":"2014-03-21T20:54:50+00:00","duration":0.097},{"name":"sql.active_record","payload":{"sql":"SELECT  \"users\".* FROM \"users\"  WHERE \"users\".\"id\" = 2 LIMIT 1","binds":[],"name":"CACHE","connection_id":70131598302600},"time":"2014-03-21T20:54:50+00:00","transaction_id":"7f33f7331d54e38ffd6f","end":"2014-03-21T20:54:50+00:00","duration":0.002},{"name":"sql.active_record","payload":{"sql":"SELECT  \"users\".* FROM \"users\"  WHERE \"users\".\"id\" = 2 LIMIT 1","binds":[],"name":"CACHE","connection_id":70131598302600},"time":"2014-03-21T20:54:50+00:00","transaction_id":"7f33f7331d54e38ffd6f","end":"2014-03-21T20:54:50+00:00","duration":0.0},{"name":"sql.active_record","payload":{"sql":"SELECT  \"users\".* FROM \"users\"  WHERE \"users\".\"id\" = 1 LIMIT 1","binds":[],"name":"CACHE","connection_id":70131598302600},"time":"2014-03-21T20:54:50+00:00","transaction_id":"7f33f7331d54e38ffd6f","end":"2014-03-21T20:54:50+00:00","duration":0.001},{"name":"sql.active_record","payload":{"sql":"SELECT \"images\".* FROM \"images\"  WHERE \"images\".\"product_id\" = 38","name":"Image Load","connection_id":70131598302600,"binds":[]},"time":"2014-03-21T20:54:50+00:00","transaction_id":"a5fe53095b653099bcf1","end":"2014-03-21T20:54:50+00:00","duration":0.093},{"name":"sql.active_record","payload":{"sql":"SELECT  \"users\".* FROM \"users\"  WHERE \"users\".\"id\" = 1 LIMIT 1","binds":[],"name":"CACHE","connection_id":70131598302600},"time":"2014-03-21T20:54:50+00:00","transaction_id":"7f33f7331d54e38ffd6f","end":"2014-03-21T20:54:50+00:00","duration":0.001},{"name":"sql.active_record","payload":{"sql":"SELECT \"images\".* FROM \"images\"  WHERE \"images\".\"product_id\" = 41","name":"Image Load","connection_id":70131598302600,"binds":[]},"time":"2014-03-21T20:54:50+00:00","transaction_id":"a5fe53095b653099bcf1","end":"2014-03-21T20:54:50+00:00","duration":0.06999999999999999},{"name":"sql.active_record","payload":{"sql":"SELECT  \"users\".* FROM \"users\"  WHERE \"users\".\"id\" = 1 LIMIT 1","binds":[],"name":"CACHE","connection_id":70131598302600},"time":"2014-03-21T20:54:50+00:00","transaction_id":"7f33f7331d54e38ffd6f","end":"2014-03-21T20:54:50+00:00","duration":0.001},{"name":"sql.active_record","payload":{"sql":"SELECT \"images\".* FROM \"images\"  WHERE \"images\".\"product_id\" = 42","name":"Image Load","connection_id":70131598302600,"binds":[]},"time":"2014-03-21T20:54:50+00:00","transaction_id":"a5fe53095b653099bcf1","end":"2014-03-21T20:54:50+00:00","duration":0.06499999999999999},{"name":"sql.active_record","payload":{"sql":"SELECT \"images\".* FROM \"images\"  WHERE \"images\".\"product_id\" = 37","name":"Image Load","connection_id":70131598302600,"binds":[]},"time":"2014-03-21T20:54:50+00:00","transaction_id":"a5fe53095b653099bcf1","end":"2014-03-21T20:54:50+00:00","duration":0.06499999999999999},{"name":"sql.active_record","payload":{"sql":"SELECT \"images\".* FROM \"images\"  WHERE \"images\".\"product_id\" = 39","name":"Image Load","connection_id":70131598302600,"binds":[]},"time":"2014-03-21T20:54:50+00:00","transaction_id":"a5fe53095b653099bcf1","end":"2014-03-21T20:54:50+00:00","duration":0.064},{"name":"sql.active_record","payload":{"sql":"SELECT \"images\".* FROM \"images\"  WHERE \"images\".\"product_id\" = 40","name":"Image Load","connection_id":70131598302600,"binds":[]},"time":"2014-03-21T20:54:50+00:00","transaction_id":"a5fe53095b653099bcf1","end":"2014-03-21T20:54:50+00:00","duration":0.078},{"name":"sql.active_record","payload":{"sql":"SELECT COUNT(*) FROM \"offers\"  WHERE (completed = 'n')","name":null,"connection_id":70131598302600,"binds":[]},"time":"2014-03-21T20:54:50+00:00","transaction_id":"a5fe53095b653099bcf1","end":"2014-03-21T20:54:50+00:00","duration":0.073},{"name":"render_partial.action_view","payload":{"identifier":"/Users/Nikolas/.rbenv/versions/2.0.0-p247/lib/ruby/gems/2.0.0/gems/kaminari-0.15.1/app/views/kaminari/_paginator.html.erb"},"time":"2014-03-21T20:54:50+00:00","transaction_id":"7f33f7331d54e38ffd6f","end":"2014-03-21T20:54:50+00:00","duration":0.029},{"name":"render_template.action_view","payload":{"identifier":"/Users/Nikolas/Desktop/FinalProject/app/views/offers/index.html.erb","layout":"layouts/application"},"time":"2014-03-21T20:54:50+00:00","transaction_id":"7f33f7331d54e38ffd6f","end":"2014-03-21T20:54:50+00:00","duration":21.941},{"name":"sql.active_record","payload":{"sql":"SELECT \"categories\".* FROM \"categories\" ","name":"Category Load","connection_id":70131598302600,"binds":[]},"time":"2014-03-21T20:54:50+00:00","transaction_id":"a5fe53095b653099bcf1","end":"2014-03-21T20:54:50+00:00","duration":0.103},{"name":"process_action.action_controller","payload":{"controller":"OffersController","action":"index","params":{"action":"index","controller":"offers"},"format":"html","method":"GET","path":"/offers","status":200,"view_runtime":31.865,"db_runtime":1.3609999999999998},"time":"2014-03-21T20:54:50+00:00","transaction_id":"7f33f7331d54e38ffd6f","end":"2014-03-21T20:54:50+00:00","duration":33.764}]